dialogic/__init__.py
dialogic/criteria.py
dialogic/dialog_connector.py
dialogic/adapters/__init__.py
dialogic/adapters/alice.py
dialogic/adapters/base.py
dialogic/adapters/facebook.py
dialogic/adapters/salut.py
dialogic/adapters/text.py
dialogic/adapters/tg.py
dialogic/adapters/vk.py
dialogic/cascade/__init__.py
dialogic/cascade/cascade.py
dialogic/cascade/turn.py
dialogic/dialog/__init__.py
dialogic/dialog/context.py
dialogic/dialog/names.py
dialogic/dialog/phrase.py
dialogic/dialog/response.py
dialogic/dialog/serialized_message.py
dialogic/dialog_manager/__init__.py
dialogic/dialog_manager/automaton.py
dialogic/dialog_manager/base.py
dialogic/dialog_manager/faq.py
dialogic/dialog_manager/form_filling.py
dialogic/dialog_manager/turning.py
dialogic/interfaces/__init__.py
dialogic/interfaces/vk.py
dialogic/interfaces/yandex/__init__.py
dialogic/interfaces/yandex/request.py
dialogic/interfaces/yandex/response.py
dialogic/nlg/__init__.py
dialogic/nlg/controls.py
dialogic/nlg/morph.py
dialogic/nlg/reply_markup.py
dialogic/nlg/sampling.py
dialogic/nlu/__init__.py
dialogic/nlu/basic_nlu.py
dialogic/nlu/matchers.py
dialogic/nlu/regex_expander.py
dialogic/nlu/regex_utils.py
dialogic/server/__init__.py
dialogic/server/flask_ngrok.py
dialogic/server/flask_server.py
dialogic/storage/__init__.py
dialogic/storage/database_utils.py
dialogic/storage/message_logging.py
dialogic/storage/session_storage.py
dialogic/testing/__init__.py
dialogic/testing/testing_utils.py
dialogic/utils/__init__.py
dialogic/utils/collections.py
dialogic/utils/configuration.py
dialogic/utils/content_manager.py
dialogic/utils/database_utils.py
dialogic/utils/serialization.py
dialogic/utils/text.py
tests/__init__.py
tests/test_cascade.py
tests/test_connector.py
tests/test_controls.py
tests/test_flask_server.py
tests/test_image_manager.py
tests/test_message_logging.py
tests/test_nlg_markup.py
tests/test_phrase.py
tests/test_utils.py
tests/test_managers/__init__.py
tests/test_managers/test_faq.py
dialogic-0.3.0.dist-info/LICENSE
dialogic-0.3.0.dist-info/METADATA
dialogic-0.3.0.dist-info/WHEEL
dialogic-0.3.0.dist-info/top_level.txt
dialogic-0.3.0.dist-info/RECORD
