Metadata-Version: 2.1
Name: dialogic
Version: 0.3.0
Summary: Yet another common wrapper for Alice/Salut skills and Facebook/Telegram/VK bots
Home-page: https://github.com/avidale/dialogic
Author: David Dale
Author-email: dale.david@mail.ru
License: MIT
Platform: UNKNOWN
Classifier: Development Status :: 3 - Alpha
Classifier: Programming Language :: Python :: 3
Classifier: License :: OSI Approved :: MIT License
Classifier: Operating System :: OS Independent
Requires-Dist: attrs
Requires-Dist: flask
Requires-Dist: pymessenger
Requires-Dist: pymorphy2
Requires-Dist: pyTelegramBotAPI
Requires-Dist: pyyaml
Requires-Dist: requests
Requires-Dist: textdistance
Requires-Dist: colorama
Provides-Extra: rumorph
Requires-Dist: pymorphy2[fast] ; extra == 'rumorph'
Requires-Dist: pymorphy2-dicts-ru ; extra == 'rumorph'
Provides-Extra: server
Requires-Dist: flask ; extra == 'server'
Requires-Dist: pymessenger ; extra == 'server'
Requires-Dist: pyTelegramBotAPI ; extra == 'server'
Provides-Extra: w2v
Requires-Dist: numpy ; extra == 'w2v'
Requires-Dist: pyemd ; extra == 'w2v'
